{
  "go.thatako.net": [
    {
      "t": 1773038723,
      "ms": 25,
      "up": true
    },
    {
      "t": 1773042138,
      "ms": 99,
      "up": true
    },
    {
      "t": 1773045022,
      "ms": 106,
      "up": true
    },
    {
      "t": 1773048942,
      "ms": 163,
      "up": true
    },
    {
      "t": 1773052396,
      "ms": 61,
      "up": true
    },
    {
      "t": 1773055586,
      "ms": 137,
      "up": true
    },
    {
      "t": 1773059499,
      "ms": 156,
      "up": true
    },
    {
      "t": 1773064622,
      "ms": 114,
      "up": true
    },
    {
      "t": 1773067424,
      "ms": 67,
      "up": true
    },
    {
      "t": 1773071086,
      "ms": 104,
      "up": true
    },
    {
      "t": 1773074636,
      "ms": 110,
      "up": true
    },
    {
      "t": 1773077918,
      "ms": 46,
      "up": true
    },
    {
      "t": 1773081314,
      "ms": 117,
      "up": true
    },
    {
      "t": 1773084703,
      "ms": 71,
      "up": true
    },
    {
      "t": 1773087574,
      "ms": 53,
      "up": true
    },
    {
      "t": 1773091270,
      "ms": 197,
      "up": true
    },
    {
      "t": 1773094588,
      "ms": 191,
      "up": true
    },
    {
      "t": 1773098168,
      "ms": 39,
      "up": true
    },
    {
      "t": 1773104184,
      "ms": 47,
      "up": true
    },
    {
      "t": 1773112923,
      "ms": 104,
      "up": true
    },
    {
      "t": 1773119044,
      "ms": 90,
      "up": true
    },
    {
      "t": 1773124390,
      "ms": 112,
      "up": true
    }
  ],
  "thatako.net": [
    {
      "t": 1773038723,
      "ms": 173,
      "up": true
    },
    {
      "t": 1773042138,
      "ms": 206,
      "up": true
    },
    {
      "t": 1773045022,
      "ms": 226,
      "up": true
    },
    {
      "t": 1773048942,
      "ms": 85,
      "up": true
    },
    {
      "t": 1773052396,
      "ms": 422,
      "up": true
    },
    {
      "t": 1773055586,
      "ms": 242,
      "up": true
    },
    {
      "t": 1773059499,
      "ms": 146,
      "up": true
    },
    {
      "t": 1773064622,
      "ms": 150,
      "up": true
    },
    {
      "t": 1773067424,
      "ms": 205,
      "up": true
    },
    {
      "t": 1773071086,
      "ms": 176,
      "up": true
    },
    {
      "t": 1773074636,
      "ms": 143,
      "up": true
    },
    {
      "t": 1773077918,
      "ms": 160,
      "up": true
    },
    {
      "t": 1773081314,
      "ms": 153,
      "up": true
    },
    {
      "t": 1773084703,
      "ms": 226,
      "up": true
    },
    {
      "t": 1773087574,
      "ms": 133,
      "up": true
    },
    {
      "t": 1773091270,
      "ms": 140,
      "up": true
    },
    {
      "t": 1773094588,
      "ms": 154,
      "up": true
    },
    {
      "t": 1773098168,
      "ms": 181,
      "up": true
    },
    {
      "t": 1773104184,
      "ms": 156,
      "up": true
    },
    {
      "t": 1773112923,
      "ms": 200,
      "up": true
    },
    {
      "t": 1773119044,
      "ms": 217,
      "up": true
    },
    {
      "t": 1773124390,
      "ms": 219,
      "up": true
    }
  ],
  "status.thatako.net": [
    {
      "t": 1773038723,
      "ms": 92,
      "up": true
    },
    {
      "t": 1773042138,
      "ms": 105,
      "up": true
    },
    {
      "t": 1773045022,
      "ms": 106,
      "up": true
    },
    {
      "t": 1773048942,
      "ms": 95,
      "up": true
    },
    {
      "t": 1773052396,
      "ms": 125,
      "up": true
    },
    {
      "t": 1773055586,
      "ms": 85,
      "up": true
    },
    {
      "t": 1773059499,
      "ms": 40,
      "up": true
    },
    {
      "t": 1773064622,
      "ms": 181,
      "up": true
    },
    {
      "t": 1773067424,
      "ms": 120,
      "up": true
    },
    {
      "t": 1773071086,
      "ms": 87,
      "up": true
    },
    {
      "t": 1773074636,
      "ms": 93,
      "up": true
    },
    {
      "t": 1773077918,
      "ms": 90,
      "up": true
    },
    {
      "t": 1773081314,
      "ms": 165,
      "up": true
    },
    {
      "t": 1773084703,
      "ms": 153,
      "up": true
    },
    {
      "t": 1773087574,
      "ms": 45,
      "up": true
    },
    {
      "t": 1773091270,
      "ms": 90,
      "up": true
    },
    {
      "t": 1773094588,
      "ms": 79,
      "up": true
    },
    {
      "t": 1773098168,
      "ms": 44,
      "up": true
    },
    {
      "t": 1773104184,
      "ms": 42,
      "up": true
    },
    {
      "t": 1773112923,
      "ms": 98,
      "up": true
    },
    {
      "t": 1773119044,
      "ms": 98,
      "up": true
    },
    {
      "t": 1773124390,
      "ms": 117,
      "up": true
    }
  ],
  "workers.thatako.net": [
    {
      "t": 1773038723,
      "ms": 43,
      "up": true
    },
    {
      "t": 1773042138,
      "ms": 29,
      "up": true
    },
    {
      "t": 1773045022,
      "ms": 110,
      "up": true
    },
    {
      "t": 1773048942,
      "ms": 40,
      "up": true
    },
    {
      "t": 1773052396,
      "ms": 51,
      "up": true
    },
    {
      "t": 1773055586,
      "ms": 123,
      "up": true
    },
    {
      "t": 1773059499,
      "ms": 30,
      "up": true
    },
    {
      "t": 1773064622,
      "ms": 73,
      "up": true
    },
    {
      "t": 1773067424,
      "ms": 27,
      "up": true
    },
    {
      "t": 1773071086,
      "ms": 85,
      "up": true
    },
    {
      "t": 1773074636,
      "ms": 54,
      "up": true
    },
    {
      "t": 1773077918,
      "ms": 90,
      "up": true
    },
    {
      "t": 1773081314,
      "ms": 182,
      "up": true
    },
    {
      "t": 1773084703,
      "ms": 57,
      "up": true
    },
    {
      "t": 1773087574,
      "ms": 38,
      "up": true
    },
    {
      "t": 1773091270,
      "ms": 77,
      "up": true
    },
    {
      "t": 1773094588,
      "ms": 187,
      "up": true
    },
    {
      "t": 1773098168,
      "ms": 27,
      "up": true
    },
    {
      "t": 1773104184,
      "ms": 24,
      "up": true
    },
    {
      "t": 1773112923,
      "ms": 98,
      "up": true
    },
    {
      "t": 1773119044,
      "ms": 185,
      "up": true
    },
    {
      "t": 1773124390,
      "ms": 102,
      "up": true
    }
  ],
  "workers.thatako.net/dns": [
    {
      "t": 1773038723,
      "ms": 21,
      "up": true
    },
    {
      "t": 1773042138,
      "ms": 17,
      "up": true
    },
    {
      "t": 1773045022,
      "ms": 55,
      "up": true
    },
    {
      "t": 1773048942,
      "ms": 16,
      "up": true
    },
    {
      "t": 1773052396,
      "ms": 30,
      "up": true
    },
    {
      "t": 1773055586,
      "ms": 60,
      "up": true
    },
    {
      "t": 1773059499,
      "ms": 18,
      "up": true
    },
    {
      "t": 1773064622,
      "ms": 52,
      "up": true
    },
    {
      "t": 1773067424,
      "ms": 19,
      "up": true
    },
    {
      "t": 1773071086,
      "ms": 39,
      "up": true
    },
    {
      "t": 1773074636,
      "ms": 35,
      "up": true
    },
    {
      "t": 1773077918,
      "ms": 18,
      "up": true
    },
    {
      "t": 1773081314,
      "ms": 50,
      "up": true
    },
    {
      "t": 1773084703,
      "ms": 36,
      "up": true
    },
    {
      "t": 1773087574,
      "ms": 16,
      "up": true
    },
    {
      "t": 1773091270,
      "ms": 55,
      "up": true
    },
    {
      "t": 1773094588,
      "ms": 56,
      "up": true
    },
    {
      "t": 1773098168,
      "ms": 15,
      "up": true
    },
    {
      "t": 1773104184,
      "ms": 15,
      "up": true
    },
    {
      "t": 1773112923,
      "ms": 39,
      "up": true
    },
    {
      "t": 1773119044,
      "ms": 54,
      "up": true
    },
    {
      "t": 1773124390,
      "ms": 38,
      "up": true
    }
  ]
}